tests/__init__.py
tests/test_core.py
tests/test_track.py
tests/test_utils.py
tests/test_vehicle.py
wa_simulator/__init__.py
wa_simulator/_import.py
wa_simulator/_version.py
wa_simulator/base.py
wa_simulator/bridge.py
wa_simulator/controller.py
wa_simulator/core.py
wa_simulator/environment.py
wa_simulator/path.py
wa_simulator/sensor.py
wa_simulator/simulation.py
wa_simulator/system.py
wa_simulator/track.py
wa_simulator/utils.py
wa_simulator/vehicle.py
wa_simulator/vehicle_inputs.py
wa_simulator/visualization.py
wa_simulator/chrono/__init__.py
wa_simulator/chrono/controller.py
wa_simulator/chrono/environment.py
wa_simulator/chrono/sensor.py
wa_simulator/chrono/system.py
wa_simulator/chrono/utils.py
wa_simulator/chrono/vehicle.py
wa_simulator/chrono/visualization.py
wa_simulator-2.3.7.dist-info/LICENSE
wa_simulator-2.3.7.dist-info/METADATA
wa_simulator-2.3.7.dist-info/WHEEL
wa_simulator-2.3.7.dist-info/top_level.txt
wa_simulator-2.3.7.dist-info/RECORD
