Metadata-Version: 2.1
Name: wa-simulator
Version: 2.3.7
Summary: Simulation tool for prototyping autonomous vehicle related algorithms.
Home-page: UNKNOWN
Author: Wisconsin Autonomous
Author-email: wisconsinautonomous@studentorg.wisc.edu
License: BSD3
Project-URL: Homepage, https://github.com/WisconsinAutonomous/wa_simulator/
Project-URL: Documentation, https://WisconsinAutononomous.github.io/wa_simulator
Project-URL: Bug Reports, https://github.com/WisconsinAutonomous/wa_simulator/issues
Project-URL: Source Code, https://github.com/WisconsinAutonomous/wa_simulator/
Project-URL: Our Team!, https://wa.wisc.edu
Keywords: simulation,autonomous vehicles,robotics
Platform: UNKNOWN
Classifier: Development Status :: 3 - Alpha
Classifier: Topic :: Software Development
Classifier: License :: OSI Approved :: BSD License
Classifier: Programming Language :: Python :: 3
Requires-Python: >=3.0
License-File: LICENSE
Requires-Dist: wa-simulator
Requires-Dist: setuptools-scm (>=6.3.2)
Requires-Dist: matplotlib (>=3.3.2)
Requires-Dist: scipy (>=1.7)
Requires-Dist: numpy (>=1.19)
Requires-Dist: IPython (>=7.28.0)
Requires-Dist: pyrr (==0.10.3)
Requires-Dist: dill (==0.3.4)
Requires-Dist: docker (>=5.0.3)
Requires-Dist: pyyaml (>=6.0)
Requires-Dist: black
